README.rst
setup.py
clarent/__init__.py
clarent/_version.py
clarent/certificate.py
clarent/exercise.py
clarent/path.py
clarent.egg-info/PKG-INFO
clarent.egg-info/SOURCES.txt
clarent.egg-info/dependency_links.txt
clarent.egg-info/requires.txt
clarent.egg-info/top_level.txt
clarent.egg-info/zip-safe
clarent/test/__init__.py
clarent/test/test_certificate.py
clarent/test/test_exercise.py
clarent/test/test_path.py